cpu15/ram_dc_wb.v
module ram_dc_wb(CLK_DC,
                 CLK_WB,
                 RAM_ADDR,
                 RAM_IN,
                 IO65_IN,
                 RAM_WEN,
                 RAM_OUT,
                 IO64_OUT
);
    input           CLK_DC;
    input           CLK_WB;
    input   [15:0]  RAM_ADDR;
    input   [15:0]  RAM_IN;
    input   [15:0]  IO65_IN;
    input           RAM_WEN;
    output  [15:0]  RAM_OUT;
    output  [15:0]  IO64_OUT;

    reg     [15:0]  RAM_OUT;
    reg     [15:0]  IO64_OUT;

    reg     [15:0]  RAM_ARRAY[63:0];
    integer         ADDR_INT;


    // 配列RAM_ARRAYの読み出し処理
    always @(posedge CLK_DC) begin
        ADDR_INT = RAM_ADDR;
        if (ADDR_INT < 64)
            RAM_OUT <= RAM_ARRAY[RAM_ADDR];
        else if (ADDR_INT == 64)
            RAM_OUT <= IO65_IN;
    end

    // 配列RAM_ARRAYの書き込み処理
    always @(posedge CLK_WB) begin
        if (ADDR_INT < 64)
            RAM_ARRAY[ADDR_INT] <= RAM_IN;
        else if (ADDR_INT == 64)
            IO64_OUT <= RAM_IN;
    end

endmodule

cpu15/test/test_ram_dc_wb.v
// `include "../ram_dc_wb.v"

module RAM_DC_WB_TEST();
    reg             clk_dc;
    reg             clk_wb;
    reg     [15:0]  ram_addr;
    reg     [15:0]  ram_in;
    reg     [15:0]  io65_in;
    reg             ram_wen;
    wire    [15:0]  ram_out;
    wire    [15:0]  io64_out;

    ram_dc_wb ram_dc_wb_inst(
        .CLK_DC(clk_dc),
        .CLK_WB(clk_wb),
        .RAM_ADDR(ram_addr),
        .RAM_IN(ram_in),
        .IO65_IN(io65_in),
        .RAM_WEN(ram_wen),
        .RAM_OUT(ram_out),
        .IO64_OUT(io64_out)
    );

    initial begin
        $dumpfile("./test/test_ram_dc_wb.vcd");
        $dumpvars(0, ram_dc_wb_inst);
        $monitor("%t: ram_addr=%h, ram_in=%h, io65_in=%h => ram_wen=%b, ram_out=%h, io64_out=%h", $time, ram_addr, ram_in, io65_in, ram_wen, ram_out, io64_out);
    end

    always #5 begin
        clk_dc <= !clk_dc;
        clk_wb <= !clk_wb;
    end

    // 入力信号clk_dcの波形
    initial begin
        clk_dc <= 1'b0;
      #10
        clk_dc <= 1'b1;
      #10
        clk_dc <= 1'b0;
    end

    // 入力信号clk_wbの波形
    initial begin
        clk_wb <= 1'b0;
      #30
        clk_dc <= 1'b1;
      
    end

    // 入力信号ram_addrの波形
    integer   i, j;
    initial begin
        // integer   i, j;
        for (i = 0; i < 1; i = i + 1) begin
            ram_addr <= 16'b0000000000000000;
            for (j = 0; j < 16; j = j + 1) begin
              #40
                ram_addr <= ram_addr + 16'b0000000000000001;
            end
        end
    end

    // 入力信号ram_inの波形
    initial begin
        ram_in <= 16'b0000000000000010;
      #40
        ram_in <= 16'b0000000000000100;
      #40
        ram_in <= 16'b0000000000000110;
      #40
        ram_in <= 16'b0000000000001000;
      #40
        ram_in <= 16'b0000000000000111;
      #40
        ram_in <= 16'b0000000000000101;
      #40
        ram_in <= 16'b0000000000000011;
    end

    // 入力信号ram_wenの波形
    initial begin
        ram_wen <= 1'b1;
      #640
        ram_wen <= 1'b0;
      #640
      $finish;
    end

endmodule

cpu15/test/test_ram_dc_wb.vcd
$date
	Sat Oct 24 17:55:05 2020
$end
$version
	Icarus Verilog
$end
$timescale
	1s
$end
$scope module RAM_DC_WB_TEST $end
$scope module ram_dc_wb_inst $end
$var wire 1 ! CLK_DC $end
$var wire 1 " CLK_WB $end
$var wire 16 # IO65_IN [15:0] $end
$var wire 16 $ RAM_ADDR [15:0] $end
$var wire 16 % RAM_IN [15:0] $end
$var wire 1 & RAM_WEN $end
$var reg 16 ' IO64_OUT [15:0] $end
$var reg 16 ( RAM_OUT [15:0] $end
$var integer 32 ) ADDR_INT [31:0] $end
$upscope $end
$upscope $end
$enddefinitions $end
#0
$dumpvars
bx )
bx (
bx '
1&
b10 %
b0 $
bx #
0"
0!
$end
#5
b0 )
1"
1!
#10
0"
0!
#15
b10 (
1"
1!
#20
0"
0!
#25
1"
1!
#30
0"
0!
#35
1"
1!
#40
0"
0!
b100 %
b1 $
#45
bx (
b1 )
1"
1!
#50
0"
0!
#55
b100 (
1"
1!
#60
0"
0!
#65
1"
1!
#70
0"
0!
#75
1"
1!
#80
0"
0!
b110 %
b10 $
#85
bx (
b10 )
1"
1!
#90
0"
0!
#95
b110 (
1"
1!
#100
0"
0!
#105
1"
1!
#110
0"
0!
#115
1"
1!
#120
0"
0!
b1000 %
b11 $
#125
bx (
b11 )
1"
1!
#130
0"
0!
#135
b1000 (
1"
1!
#140
0"
0!
#145
1"
1!
#150
0"
0!
#155
1"
1!
#160
0"
0!
b111 %
b100 $
#165
bx (
b100 )
1"
1!
#170
0"
0!
#175
b111 (
1"
1!
#180
0"
0!
#185
1"
1!
#190
0"
0!
#195
1"
1!
#200
0"
0!
b101 %
b101 $
#205
bx (
b101 )
1"
1!
#210
0"
0!
#215
b101 (
1"
1!
#220
0"
0!
#225
1"
1!
#230
0"
0!
#235
1"
1!
#240
0"
0!
b11 %
b110 $
#245
bx (
b110 )
1"
1!
#250
0"
0!
#255
b11 (
1"
1!
#260
0"
0!
#265
1"
1!
#270
0"
0!
#275
1"
1!
#280
0"
0!
b111 $
#285
bx (
b111 )
1"
1!
#290
0"
0!
#295
b11 (
1"
1!
#300
0"
0!
#305
1"
1!
#310
0"
0!
#315
1"
1!
#320
0"
0!
b1000 $
#325
bx (
b1000 )
1"
1!
#330
0"
0!
#335
b11 (
1"
1!
#340
0"
0!
#345
1"
1!
#350
0"
0!
#355
1"
1!
#360
0"
0!
b1001 $
#365
bx (
b1001 )
1"
1!
#370
0"
0!
#375
b11 (
1"
1!
#380
0"
0!
#385
1"
1!
#390
0"
0!
#395
1"
1!
#400
0"
0!
b1010 $
#405
bx (
b1010 )
1"
1!
#410
0"
0!
#415
b11 (
1"
1!
#420
0"
0!
#425
1"
1!
#430
0"
0!
#435
1"
1!
#440
0"
0!
b1011 $
#445
bx (
b1011 )
1"
1!
#450
0"
0!
#455
b11 (
1"
1!
#460
0"
0!
#465
1"
1!
#470
0"
0!
#475
1"
1!
#480
0"
0!
b1100 $
#485
bx (
b1100 )
1"
1!
#490
0"
0!
#495
b11 (
1"
1!
#500
0"
0!
#505
1"
1!
#510
0"
0!
#515
1"
1!
#520
0"
0!
b1101 $
#525
bx (
b1101 )
1"
1!
#530
0"
0!
#535
b11 (
1"
1!
#540
0"
0!
#545
1"
1!
#550
0"
0!
#555
1"
1!
#560
0"
0!
b1110 $
#565
bx (
b1110 )
1"
1!
#570
0"
0!
#575
b11 (
1"
1!
#580
0"
0!
#585
1"
1!
#590
0"
0!
#595
1"
1!
#600
0"
0!
b1111 $
#605
bx (
b1111 )
1"
1!
#610
0"
0!
#615
b11 (
1"
1!
#620
0"
0!
#625
1"
1!
#630
0"
0!
#635
1"
1!
#640
0"
0!
b10000 $
0&
#645
bx (
b10000 )
1"
1!
#650
0"
0!
#655
b11 (
1"
1!
