cpu15/ram_wb.v
module ram_wb(CLK_WB,
              RAM_ADDR,
              RAM_IN,
              RAM_WEN,
              RAM_0,
              RAM_1,
              RAM_2,
              RAM_3,
              RAM_4,
              RAM_5,
              RAM_6,
              RAM_7,
              IO64_OUT);
    input           CLK_WB;
    input   [7:0]   RAM_ADDR;
    input   [15:0]  RAM_IN;
    input           RAM_WEN;
    output  [15:0]  RAM_0, RAM_1, RAM_2, RAM_3, RAM_4, RAM_5, RAM_6, RAM_7;
    output  [15:0]  IO64_OUT;

    reg     [15:0]  RAM_0, RAM_1, RAM_2, RAM_3, RAM_4, RAM_5, RAM_6, RAM_7;
    reg     [15:0]  IO64_OUT;

    always @ (posedge CLK_WB) begin
        if (RAM_WEN == 1'b1) begin
            case (RAM_ADDR)
                8'b00000000: RAM_0 <= RAM_IN;
                8'b00000001: RAM_1 <= RAM_IN;
                8'b00000010: RAM_2 <= RAM_IN;
                8'b00000011: RAM_3 <= RAM_IN;
                8'b00000100: RAM_4 <= RAM_IN;
                8'b00000101: RAM_5 <= RAM_IN;
                8'b00000110: RAM_6 <= RAM_IN;
                8'b00000111: RAM_7 <= RAM_IN;
                8'b01000000: IO64_OUT <= RAM_IN;
            endcase
        end
    end

endmodule

cpu15/test_ram_wb.v
module RAM_WB_TEST();
    reg             clk_wb;
    reg     [7:0]   ram_addr;
    reg     [15:0]  ram_in;
    reg             ram_wen;
    wire    [15:0]  ram_0;
    wire    [15:0]  ram_1;
    wire    [15:0]  ram_2;
    wire    [15:0]  ram_3;
    wire    [15:0]  ram_4;
    wire    [15:0]  ram_5;
    wire    [15:0]  ram_6;
    wire    [15:0]  ram_7;
    wire    [15:0]  io64_out;

    ram_wb ram_wb_inst(
        .CLK_WB(clk_wb),
        .RAM_ADDR(ram_addr),
        .RAM_IN(ram_in),
        .RAM_WEN(ram_wen),
        .RAM_0(ram_0),
        .RAM_1(ram_1),
        .RAM_2(ram_2),
        .RAM_3(ram_3),
        .RAM_4(ram_4),
        .RAM_5(ram_5),
        .RAM_6(ram_6),
        .RAM_7(ram_7),
        .IO64_OUT(io64_out)
    );

    initial begin
        $dumpfile("test_ram_wb.vcd");
        $dumpvars(0, ram_wb_inst);
        $monitor("%t: ram_addr=%h, ram_in=%h, ram_wen=%b => ram_0=%h, ram_1=%h, ram_2=%h, ram_3=%h, ram_4=%h, ram_5=%h, ram_6=%h, ram_7=%h, io64_out=%h", $time, ram_addr, ram_in, ram_wen, ram_0, ram_1, ram_2, ram_3, ram_4, ram_5, ram_6, ram_7, io64_out);
    end

    // テスト信号の発生
    initial begin
        clk_wb <= 1'b0;
    end

    always #5 begin
        clk_wb <= !clk_wb;
    end

    initial begin
      #10
        ram_addr <= 8'b00000000;
        ram_in <= 16'hbeaf;
        ram_wen <= 1'b0;
      #10
        ram_addr <= 8'b00000001;
        ram_in <= 16'hbeaf;
        ram_wen <= 1'b1;
      #10
        ram_addr <= 8'b00000010;
        ram_in <= 16'hbeaf;
        ram_wen <= 1'b0;
      #10
        ram_addr <= 8'b00000011;
        ram_in <= 16'hbeaf;
        ram_wen <= 1'b1;
      #10
        ram_addr <= 8'b00000100;
        ram_in <= 16'hbeaf;
        ram_wen <= 1'b0;
      #10
        ram_addr <= 8'b00000101;
        ram_in <= 16'hbeaf;
        ram_wen <= 1'b1;
      #10
        ram_addr <= 8'b00000110;
        ram_in <= 16'hbeaf;
        ram_wen <= 1'b0;
      #10
        ram_addr <= 8'b00000111;
        ram_in <= 16'hbeaf;
        ram_wen <= 1'b1;
      #10
        ram_addr <= 8'b01000000;
        ram_in <= 16'hcafe;
      #10
      $finish;
    end

endmodule

cpu15/test/test_ram_wb.vcd
$date
	Sat Sep 19 16:47:13 2020
$end
$version
	Icarus Verilog
$end
$timescale
	1s
$end
$scope module RAM_WB_TEST $end
$scope module ram_wb_inst $end
$var wire 1 ! CLK_WB $end
$var wire 8 " RAM_ADDR [7:0] $end
$var wire 16 # RAM_IN [15:0] $end
$var wire 1 $ RAM_WEN $end
$var reg 16 % IO64_OUT [15:0] $end
$var reg 16 & RAM_0 [15:0] $end
$var reg 16 ' RAM_1 [15:0] $end
$var reg 16 ( RAM_2 [15:0] $end
$var reg 16 ) RAM_3 [15:0] $end
$var reg 16 * RAM_4 [15:0] $end
$var reg 16 + RAM_5 [15:0] $end
$var reg 16 , RAM_6 [15:0] $end
$var reg 16 - RAM_7 [15:0] $end
$upscope $end
$upscope $end
$enddefinitions $end
#0
$dumpvars
bx -
bx ,
bx +
bx *
bx )
bx (
bx '
bx &
bx %
x$
bx #
bx "
0!
$end
#5
1!
#10
0!
0$
b1011111010101111 #
b0 "
#15
1!
#20
0!
1$
b1 "
#25
b1011111010101111 '
1!
#30
0!
0$
b10 "
#35
1!
#40
0!
1$
b11 "
#45
b1011111010101111 )
1!
#50
0!
0$
b100 "
#55
1!
#60
0!
1$
b101 "
#65
b1011111010101111 +
1!
#70
0!
0$
b110 "
#75
1!
#80
0!
1$
b111 "
#85
b1011111010101111 -
1!
#90
0!
b1100101011111110 #
b1000000 "
#95
b1100101011111110 %
1!
