cpu15/exec.v
`define MOV     4'h0
`define ADD     4'h1
`define SUB     4'h2
`define AND     4'h3
`define OR      4'h4
`define SL      4'h5
`define SR      4'h6
`define SRA     4'h7
`define LDL     4'h8
`define LDH     4'h9
`define CMP     4'ha
`define JE      4'hb
`define JMP     4'hc
`define LD      4'hd
`define ST      4'he
`define HLT     4'hf


module exec(CLK_EX,
            RESET_N,
            OP_CODE,
            REG_A,
            REG_B,
            OP_DATA,
            RAM_OUT,
            P_COUNT,
            REG_IN,
            RAM_IN,
            REG_WEN,
            RAM_WEN);
    input           CLK_EX;
    input           RESET_N;
    input   [3:0]   OP_CODE;
    input   [15:0]  REG_A;
    input   [15:0]  REG_B;
    input   [7:0]   OP_DATA;
    input   [15:0]  RAM_OUT;
    output  [7:0]   P_COUNT;
    output  [15:0]  REG_IN;
    output  [15:0]  RAM_IN;
    output          REG_WEN;
    output          RAM_WEN;

    wire    [7:0]   P_COUNT;
    reg     [15:0]  REG_IN;
    reg     [15:0]  RAM_IN;
    reg             REG_WEN;
    reg             RAM_WEN;

    reg     [7:0]   pc = 8'h00;
    reg             cmp_flag = 1'b0;

    always @ (posedge CLK_EX) begin
        if (RESET_N == 1'b0) begin
            pc <= 8'h00;
            cmp_flag <= 1'b0;
        end 
        else begin
            case (OP_CODE)
                `MOV: begin
                    REG_IN <= REG_B;
                    REG_WEN <= 1'b1;
                    RAM_WEN <= 1'b0;
                    pc <= pc + 8'h1;
                end
                `ADD: begin
                    REG_IN <= REG_A + REG_B;
                    REG_WEN <= 1'b1;
                    RAM_WEN <= 1'b0;
                    pc <= pc + 1'b1;
                end
                `SUB: begin
                    REG_IN <= REG_A - REG_B;
                    REG_WEN <= 1'b1;
                    RAM_WEN <= 1'b0;
                    pc <= pc + 1'b1;
                end
                `AND: begin
                    REG_IN <= REG_A & REG_B;
                    REG_WEN <= 1'b1;
                    RAM_WEN <= 1'b0;
                    pc <= pc + 1'b1;
                end
                `OR: begin
                    REG_IN <= REG_A | REG_B;
                    REG_WEN <= 1'b1;
                    RAM_WEN <= 1'b0;
                    pc <= pc + 1'b1;
                end
                `SL: begin
                    REG_IN <= REG_A << 1'b1;
                    REG_WEN <= 1'b1;
                    RAM_WEN <= 1'b0;
                    pc <= pc + 1'b1;
                end
                `SR: begin
                    REG_IN <= REG_A >> 1'b1;
                    REG_WEN <= 1'b1;
                    RAM_WEN <= 1'b0;
                    pc <= pc + 1'b1;
                end
                `SRA: begin
                    REG_IN <= {REG_A[15], REG_A[15:1]};
                    REG_WEN <= 1'b1;
                    RAM_WEN <= 1'b0;
                    pc <= pc + 1'b1;
                end
                `LDL: begin
                    REG_IN <= {REG_A[15:8], OP_DATA};
                    REG_WEN <= 1'b1;
                    RAM_WEN <= 1'b0;
                    pc <= pc + 1'b1;
                end
                `LDH: begin
                    REG_IN <= {OP_DATA, REG_A[7:0]};
                    REG_WEN <= 1'b1;
                    RAM_WEN <= 1'b0;
                    pc <= pc + 1'b1;
                end
                `CMP: begin
                    if (REG_A == REG_B) begin
                        cmp_flag <= 1'b1;
                    end else begin
                        cmp_flag <= 1'b0;
                    end
                    REG_WEN <= 1'b0;
                    RAM_WEN <= 1'b0;
                    pc <= pc + 1'b1;
                end
                `JE: begin
                    if (cmp_flag == 1'b0) begin
                        pc <= OP_DATA;
                    end
                    REG_WEN <= 1'b0;
                    RAM_WEN <= 1'b0;
                end
                `JMP: begin
                    REG_WEN <= 1'b0;
                    RAM_WEN <= 1'b0;
                    pc <= OP_DATA;
                end
                `LD: begin
                    REG_IN <= RAM_OUT;
                    REG_WEN <= 1'b1;
                    RAM_WEN <= 1'b0;
                    pc <= pc + 1'b1;
                end
                `ST: begin
                    RAM_IN <= REG_A;
                    REG_WEN <= 1'b0;
                    RAM_WEN <= 1'b1;
                    pc <= pc + 1'b1;
                end
                `HLT: begin
                    REG_WEN <= 1'b0;
                    RAM_WEN <= 1'b0;
                end
                // default: 
                    // REG_IN <= 16'hxxxx;
                    // RAM_IN <= 16'hxxxx;
                    // REG_WEN <= 1'bx;
                    // RAM_WEN <= 1'bx;
                    // pc <= 8'bxx;
                // end
            endcase
        end
    end

    assign P_COUNT = pc;
    // always @(posedge CLK_EX) begin
    //     P_COUNT <= pc;
    // end

endmodule

cpu15/test/test_exec.v
`define MOV     4'h0
`define ADD     4'h1
`define SUB     4'h2
`define AND     4'h3
`define OR      4'h4
`define SL      4'h5
`define SR      4'h6
`define SRA     4'h7
`define LDL     4'h8
`define LDH     4'h9
`define CMP     4'ha
`define JE      4'hb
`define JMP     4'hc
`define LD      4'hd
`define ST      4'he
`define HLT     4'hf


module EXEC_TEST();
    reg             clk_ex;
    reg             reset_n;
    reg     [3:0]   op_code;
    reg     [15:0]  reg_a;
    reg     [15:0]  reg_b;
    reg     [7:0]   op_data;
    reg     [15:0]  ram_out;
    wire    [7:0]   p_count;
    wire    [15:0]  reg_in;
    wire    [15:0]  ram_in;
    wire            reg_wen;
    wire            ram_wen;

    exec exec_inst(
        .CLK_EX(clk_ex),
        .RESET_N(reset_n),
        .OP_CODE(op_code),
        .REG_A(reg_a),
        .REG_B(reg_b),
        .OP_DATA(op_data),
        .RAM_OUT(ram_out),
        .P_COUNT(p_count),
        .REG_IN(reg_in),
        .RAM_IN(ram_in),
        .REG_WEN(reg_wen),
        .RAM_WEN(ram_wen)
    );

    initial begin
        $dumpfile("test_exec.vcd");
        $dumpvars(0, exec_inst);
        $monitor("%t: clk_ex=%b, op_code=%b, reg_a=%h, reg_b=%h, op_data=%h, ram_out=%h => p_count=%h, reg_in=%h, ram_in=%h, reg_wen=%b, ram_wen=%b", 
                 $time, clk_ex, op_code, reg_a, reg_b, op_data, ram_out,
                 p_count, reg_in, ram_in, reg_wen, ram_wen);
    end

    // テスト信号の発生
    initial begin
        clk_ex <= 1'b0;
        reg_a <= 16'h63a8;
        reg_b <= 16'h0001;
        op_data <= 8'h00;
        ram_out <= 16'h8000;
    end

    always #5 begin
        clk_ex <= !clk_ex;
    end

    initial begin
      #10
        op_code <= `LDH;
        op_data <= 8'h23;
      #10
        op_code <= `LDL;
        op_data <= 8'h7;
      #10
        op_code <= `ADD;
      #10
        op_code <= `OR;
      #10
        op_code <= `CMP;
      #10
        reset_n <= 1'b1;
      #10
        op_code <= `ST;
      #10
      $finish;
    end

endmodule

cpu15/test/test_exec.vcd
$date
	Sat Sep 12 15:40:45 2020
$end
$version
	Icarus Verilog
$end
$timescale
	1s
$end
$scope module EXEC_TEST $end
$scope module exec_inst $end
$var wire 1 ! CLK_EX $end
$var wire 4 " OP_CODE [3:0] $end
$var wire 8 # OP_DATA [7:0] $end
$var wire 8 $ P_COUNT [7:0] $end
$var wire 16 % RAM_OUT [15:0] $end
$var wire 16 & REG_A [15:0] $end
$var wire 16 ' REG_B [15:0] $end
$var wire 1 ( RESET_N $end
$var reg 16 ) RAM_IN [15:0] $end
$var reg 1 * RAM_WEN $end
$var reg 16 + REG_IN [15:0] $end
$var reg 1 , REG_WEN $end
$var reg 1 - cmp_flag $end
$var reg 8 . pc [7:0] $end
$upscope $end
$upscope $end
$enddefinitions $end
#0
$dumpvars
b0 .
0-
x,
bx +
x*
bx )
x(
b1 '
b110001110101000 &
b1000000000000000 %
b0 $
b0 #
bx "
0!
$end
#5
1!
#10
0!
b100011 #
b1001 "
#15
b1 $
b1 .
0*
1,
b10001110101000 +
1!
#20
0!
b111 #
b1000 "
#25
b10 $
b10 .
b110001100000111 +
1!
#30
0!
b1 "
#35
b11 $
b11 .
b110001110101001 +
1!
#40
0!
b100 "
#45
b100 $
b100 .
1!
#50
0!
b1010 "
#55
b101 $
b101 .
0,
1!
#60
0!
1(
#65
b110 $
b110 .
1!
#70
0!
b1110 "
#75
b111 $
b111 .
1*
b110001110101000 )
1!
