cpu15/reg_dc.v
module reg_dc(CLK_DC, N_REG_IN, 
              REG_0, REG_1, REG_2, REG_3, REG_4, REG_5, REG_6, REG_7, 
              N_REG_OUT, REG_OUT);
              
    input           CLK_DC;
    input   [2:0]   N_REG_IN;
    input   [15:0]  REG_0, REG_1, REG_2, REG_3, REG_4, REG_5, REG_6, REG_7;
    output  [2:0]   N_REG_OUT;
    output  [15:0]  REG_OUT;

    reg     [2:0]   N_REG_OUT;
    reg     [15:0]  REG_OUT;

    function [15:0] reg_out;
        input   [2:0]   n_reg_in;
        input   [15:0]  reg_0, reg_1, reg_2, reg_3, reg_4, reg_5, reg_6, reg_7;

        begin
        case (n_reg_in)
            3'b000: reg_out = reg_0;
            3'b001: reg_out = reg_1;
            3'b010: reg_out = reg_2;
            3'b011: reg_out = reg_3;
            3'b100: reg_out = reg_4;
            3'b101: reg_out = reg_5;
            3'b110: reg_out = reg_6;
            3'b111: reg_out = reg_7;
            default: reg_out = 16'bxxxx;  // 不定値
            endcase
        end
    endfunction

    always @ (posedge CLK_DC) begin
        N_REG_OUT <= N_REG_IN;
        REG_OUT <= reg_out(N_REG_IN, REG_0, REG_1, REG_2, REG_3, REG_4, REG_5, REG_6, REG_7);
    end

endmodule

cpu15/test_reg_dc.v
module REG_DC_TEST();
    reg             clk_dc;
    reg     [2:0]   n_reg_in;
    reg     [15:0]  reg_0, reg_1, reg_2, reg_3, reg_4, reg_5, reg_6, reg_7;
    wire    [2:0]   n_reg_out;
    wire    [15:0]  reg_out;

    reg_dc reg_dc_inst(
        .CLK_DC(clk_dc), 
        .N_REG_IN(n_reg_in), 
        .REG_0(reg_0),
        .REG_1(reg_1),
        .REG_2(reg_2),
        .REG_3(reg_3),
        .REG_4(reg_4),
        .REG_5(reg_5),
        .REG_6(reg_6),
        .REG_7(reg_7),
        .N_REG_OUT(n_reg_out), 
        .REG_OUT(reg_out)
    );

    initial begin
        $dumpfile("test_reg_dc.vcd");
        $dumpvars(0, reg_dc_inst);
        $monitor("%t: n_reg_in=%b => n_reg_out=%b, reg_out=%h", $time, n_reg_in, n_reg_out, reg_out);
    end    

    // テスト信号の発生
    initial begin
        clk_dc <= 1'b0;
        reg_0 <= 16'h6535;
        reg_1 <= 16'h7628;
        reg_2 <= 16'h7e6e;
        reg_3 <= 16'habcd;
        reg_4 <= 16'h64a6;
        reg_5 <= 16'h0000;
        reg_6 <= 16'h34b1;
        reg_7 <= 16'h808d;
    end

    always #5 begin
        clk_dc <= !clk_dc;
    end

    initial begin
      #10
        n_reg_in <= 3'b000;
      #10
        n_reg_in <= 3'b001;
      #10
        n_reg_in <= 3'b010;
      #10
        n_reg_in <= 3'b011;
      #10
        n_reg_in <= 3'b100;
      #10
        n_reg_in <= 3'b101;
      #10
        n_reg_in <= 3'b110;
      #10
        n_reg_in <= 3'b111;
      #10
      $finish;
    end

endmodule

cpu15/test/test_reg_dc.vcd
$date
	Sat Sep 19 16:46:53 2020
$end
$version
	Icarus Verilog
$end
$timescale
	1s
$end
$scope module REG_DC_TEST $end
$scope module reg_dc_inst $end
$var wire 1 ! CLK_DC $end
$var wire 3 " N_REG_IN [2:0] $end
$var wire 16 # REG_0 [15:0] $end
$var wire 16 $ REG_1 [15:0] $end
$var wire 16 % REG_2 [15:0] $end
$var wire 16 & REG_3 [15:0] $end
$var wire 16 ' REG_4 [15:0] $end
$var wire 16 ( REG_5 [15:0] $end
$var wire 16 ) REG_6 [15:0] $end
$var wire 16 * REG_7 [15:0] $end
$var reg 3 + N_REG_OUT [2:0] $end
$var reg 16 , REG_OUT [15:0] $end
$scope function reg_out $end
$var reg 3 - n_reg_in [2:0] $end
$var reg 16 . reg_0 [15:0] $end
$var reg 16 / reg_1 [15:0] $end
$var reg 16 0 reg_2 [15:0] $end
$var reg 16 1 reg_3 [15:0] $end
$var reg 16 2 reg_4 [15:0] $end
$var reg 16 3 reg_5 [15:0] $end
$var reg 16 4 reg_6 [15:0] $end
$var reg 16 5 reg_7 [15:0] $end
$var reg 16 6 reg_out [15:0] $end
$upscope $end
$upscope $end
$upscope $end
$enddefinitions $end
#0
$dumpvars
bx 6
bx 5
bx 4
bx 3
bx 2
bx 1
bx 0
bx /
bx .
bx -
bx ,
bx +
b1000000010001101 *
b11010010110001 )
b0 (
b110010010100110 '
b1010101111001101 &
b111111001101110 %
b111011000101000 $
b110010100110101 #
bx "
0!
$end
#5
b110010100110101 .
b111011000101000 /
b111111001101110 0
b1010101111001101 1
b110010010100110 2
b0 3
b11010010110001 4
b1000000010001101 5
1!
#10
0!
b0 "
#15
b110010100110101 ,
b0 +
b110010100110101 6
b0 -
1!
#20
0!
b1 "
#25
b111011000101000 ,
b1 +
b111011000101000 6
b1 -
1!
#30
0!
b10 "
#35
b111111001101110 ,
b10 +
b111111001101110 6
b10 -
1!
#40
0!
b11 "
#45
b1010101111001101 ,
b11 +
b1010101111001101 6
b11 -
1!
#50
0!
b100 "
#55
b110010010100110 ,
b100 +
b110010010100110 6
b100 -
1!
#60
0!
b101 "
#65
b0 ,
b101 +
b0 6
b101 -
1!
#70
0!
b110 "
#75
b11010010110001 ,
b110 +
b11010010110001 6
b110 -
1!
#80
0!
b111 "
#85
b1000000010001101 ,
b111 +
b1000000010001101 6
b111 -
1!
