cpu15/ram_dc.v
module ram_dc(CLK_DC, 
              RAM_AD_IN, 
              RAM0,
              RAM1,
              RAM2,
              RAM3,
              RAM4,
              RAM5,
              RAM6,
              RAM7,
              IO65_IN, 
              RAM_AD_OUT,
              RAM_OUT);
    input           CLK_DC;
    input   [7:0]   RAM_AD_IN;
    input   [15:0]  RAM0, RAM1, RAM2, RAM3, RAM4, RAM5, RAM6, RAM7;
    input   [15:0]  IO65_IN;
    output  [7:0]   RAM_AD_OUT;
    output  [15:0]  RAM_OUT;

    reg     [7:0]   RAM_AD_OUT;
    reg     [15:0]  RAM_OUT;

    function [15:0] ram_out;
        input   [7:0]   ram_ad_in;
        input   [15:0]  ram0, ram1, ram2, ram3, ram4, ram5, ram6, ram7;
        input   [15:0]  io65_in;

        begin
            case (ram_ad_in)
                8'b00000000: ram_out = ram0;
                8'b00000001: ram_out = ram1;
                8'b00000010: ram_out = ram2;
                8'b00000011: ram_out = ram3;
                8'b00000100: ram_out = ram4;
                8'b00000101: ram_out = ram5;
                8'b00000110: ram_out = ram6;
                8'b00000111: ram_out = ram7;
                8'b01000001: ram_out = io65_in;
                default: ram_out = 16'hxxxx;
            endcase
        end    
    endfunction

    always @ (posedge CLK_DC) begin
        RAM_AD_OUT <= RAM_AD_IN;
        RAM_OUT <= ram_out(RAM_AD_IN, RAM0, RAM1, RAM2, RAM3, RAM4, RAM5, RAM6, RAM7, IO65_IN);
    end

endmodule

cpu15/test_ram_dc.v
module RAM_DC_TEST();
    reg             clk_dc;
    reg     [7:0]   ram_ad_in;
    reg     [15:0]  ram0, ram1, ram2, ram3, ram4, ram5, ram6, ram7;
    reg     [15:0]  io65_in;
    wire    [7:0]   ram_ad_out;
    wire    [15:0]  ram_out;

    ram_dc ram_dc_inst(
        .CLK_DC(clk_dc), 
        .RAM_AD_IN(ram_ad_in), 
        .RAM0(ram0),
        .RAM1(ram1),
        .RAM2(ram2),
        .RAM3(ram3),
        .RAM4(ram4),
        .RAM5(ram5),
        .RAM6(ram6),
        .RAM7(ram7),
        .IO65_IN(io65_in),
        .RAM_AD_OUT(ram_ad_out), 
        .RAM_OUT(ram_out)
    );

    initial begin
        $dumpfile("test_ram_dc.vcd");
        $dumpvars(0, ram_dc_inst);
        $monitor("%t: ram_ad_in=%b => ram_ad_out=%b, ram_out=%h", $time, ram_ad_in, ram_ad_out, ram_out);
    end    

    // テスト信号の発生
    initial begin
        clk_dc <= 1'b0;
        ram0 <= 16'h6535;
        ram1 <= 16'h7628;
        ram2 <= 16'h7e6e;
        ram3 <= 16'habcd;
        ram4 <= 16'h64a6;
        ram5 <= 16'h0000;
        ram6 <= 16'h34b1;
        ram7 <= 16'h808d;
        io65_in <= 16'h324f;
    end

    always #5 begin
        clk_dc <= !clk_dc;
    end

    initial begin
      #10
        ram_ad_in <= 8'b00000000;
      #10
        ram_ad_in <= 8'b00000001;
      #10
        ram_ad_in <= 8'b00000010;
      #10
        ram_ad_in <= 8'b00000011;
      #10
        ram_ad_in <= 8'b00000100;
      #10
        ram_ad_in <= 8'b00000101;
      #10
        ram_ad_in <= 8'b00000110;
      #10
        ram_ad_in <= 8'b00000111;
      #10
        ram_ad_in <= 8'b01000001;
      #10
      $finish;
    end

endmodule

cpu15/test_ram_dc.vcd
$date
	Sun Sep  6 14:10:09 2020
$end
$version
	Icarus Verilog
$end
$timescale
	1s
$end
$scope module RAM_DC_TEST $end
$scope module ram_dc_inst $end
$var wire 1 ! CLK_DC $end
$var wire 16 " IO65_IN [15:0] $end
$var wire 16 # RAM0 [15:0] $end
$var wire 16 $ RAM1 [15:0] $end
$var wire 16 % RAM2 [15:0] $end
$var wire 16 & RAM3 [15:0] $end
$var wire 16 ' RAM4 [15:0] $end
$var wire 16 ( RAM5 [15:0] $end
$var wire 16 ) RAM6 [15:0] $end
$var wire 16 * RAM7 [15:0] $end
$var wire 8 + RAM_AD_IN [7:0] $end
$var reg 8 , RAM_AD_OUT [7:0] $end
$var reg 16 - RAM_OUT [15:0] $end
$scope function ram_out $end
$var reg 16 . io65_in [15:0] $end
$var reg 16 / ram0 [15:0] $end
$var reg 16 0 ram1 [15:0] $end
$var reg 16 1 ram2 [15:0] $end
$var reg 16 2 ram3 [15:0] $end
$var reg 16 3 ram4 [15:0] $end
$var reg 16 4 ram5 [15:0] $end
$var reg 16 5 ram6 [15:0] $end
$var reg 16 6 ram7 [15:0] $end
$var reg 8 7 ram_ad_in [7:0] $end
$var reg 16 8 ram_out [15:0] $end
$upscope $end
$upscope $end
$upscope $end
$enddefinitions $end
#0
$dumpvars
bx 8
bx 7
bx 6
bx 5
bx 4
bx 3
bx 2
bx 1
bx 0
bx /
bx .
bx -
bx ,
bx +
b1000000010001101 *
b11010010110001 )
b0 (
b110010010100110 '
b1010101111001101 &
b111111001101110 %
b111011000101000 $
b110010100110101 #
b11001001001111 "
0!
$end
#5
b110010100110101 /
b111011000101000 0
b111111001101110 1
b1010101111001101 2
b110010010100110 3
b0 4
b11010010110001 5
b1000000010001101 6
b11001001001111 .
1!
#10
0!
b0 +
#15
b110010100110101 -
b0 ,
b110010100110101 8
b0 7
1!
#20
0!
b1 +
#25
b111011000101000 -
b1 ,
b111011000101000 8
b1 7
1!
#30
0!
b10 +
#35
b111111001101110 -
b10 ,
b111111001101110 8
b10 7
1!
#40
0!
b11 +
#45
b1010101111001101 -
b11 ,
b1010101111001101 8
b11 7
1!
#50
0!
b100 +
#55
b110010010100110 -
b100 ,
b110010010100110 8
b100 7
1!
#60
0!
b101 +
#65
b0 -
b101 ,
b0 8
b101 7
1!
#70
0!
b110 +
#75
b11010010110001 -
b110 ,
b11010010110001 8
b110 7
1!
#80
0!
b111 +
#85
b1000000010001101 -
b111 ,
b1000000010001101 8
b111 7
1!
#90
0!
b1000001 +
#95
b11001001001111 -
b1000001 ,
b11001001001111 8
b1000001 7
1!
