cpu15/clk_gen.v
`define FT_STAGE 2'b00
`define DC_STAGE 2'b01
`define EX_STAGE 2'b10
`define WB_STAGE 2'b11


module clk_gen(CLK, CLK_FT, CLK_DC, CLK_EX, CLK_WB);
    input           CLK;
    output          CLK_FT, CLK_DC, CLK_EX, CLK_WB;

    reg             CLK_FT, CLK_DC, CLK_EX, CLK_WB;
    reg     [1:0]   cnt = 2'b00;

    function sub_clk;
        input   [1:0]   cnt;
        input   [1:0]   sel;
        
        begin
        case (cnt)
            2'b00: sub_clk = (sel == `FT_STAGE) ? 1'b1 :
                             (sel == `DC_STAGE) ? 1'b0 :
                             (sel == `EX_STAGE) ? 1'b0 :
                             (sel == `WB_STAGE) ? 1'b0 : 1'bx;

            2'b01: sub_clk = (sel == `FT_STAGE) ? 1'b0 :
                             (sel == `DC_STAGE) ? 1'b1 :
                             (sel == `EX_STAGE) ? 1'b0 :
                             (sel == `WB_STAGE) ? 1'b0 : 1'bx;

            2'b10: sub_clk = (sel == `FT_STAGE) ? 1'b0 :
                             (sel == `DC_STAGE) ? 1'b0 :
                             (sel == `EX_STAGE) ? 1'b1 :
                             (sel == `WB_STAGE) ? 1'b0 : 1'bx;

            2'b11: sub_clk = (sel == `FT_STAGE) ? 1'b0 :
                             (sel == `DC_STAGE) ? 1'b0 :
                             (sel == `EX_STAGE) ? 1'b0 :
                             (sel == `WB_STAGE) ? 1'b1 : 1'bx;

            default: sub_clk = 1'bx;
        endcase
        end        
    endfunction
    
    always @ (posedge CLK)
    begin
        cnt <= cnt + 2'b01;
        CLK_FT <= sub_clk(cnt, `FT_STAGE);
        CLK_DC <= sub_clk(cnt, `DC_STAGE);
        CLK_EX <= sub_clk(cnt, `EX_STAGE);
        CLK_WB <= sub_clk(cnt, `WB_STAGE);
    end

endmodule

cpu15/test_clk_gen.v
module CLK_GEN_TEST();
    reg     clk;
    wire    clk_ft, clk_dc, clk_ex, clk_wb;

    clk_gen clk_gen_inst(
        .CLK(clk), 
        .CLK_FT(clk_ft), 
        .CLK_DC(clk_dc), 
        .CLK_EX(clk_ex), 
        .CLK_WB(clk_wb)
    );

    initial begin
        $dumpfile("test_clk_gen.vcd");
        $dumpvars(0, clk_gen_inst);
        $monitor("%t: clk=%b => clk_ft=%b, cl_dc=%b, clk_ex=%b, clk_wb=%b", $time, clk, clk_ft, clk_dc, clk_ex, clk_wb);
    end

    always #5 begin
        clk <= !clk;
    end

    // テスト信号の発生
    initial begin
        clk <= 1'b0;
      #200
      $finish;
    end

endmodule

cpu15/test_clk_gen.vcd
$date
	Sun Sep  6 15:27:57 2020
$end
$version
	Icarus Verilog
$end
$timescale
	1s
$end
$scope module CLK_GEN_TEST $end
$scope module clk_gen_inst $end
$var wire 1 ! CLK $end
$var reg 1 " CLK_DC $end
$var reg 1 # CLK_EX $end
$var reg 1 $ CLK_FT $end
$var reg 1 % CLK_WB $end
$var reg 2 & cnt [1:0] $end
$scope function sub_clk $end
$var reg 2 ' cnt [1:0] $end
$var reg 2 ( sel [1:0] $end
$var reg 1 ) sub_clk $end
$upscope $end
$upscope $end
$upscope $end
$enddefinitions $end
#0
$dumpvars
x)
bx (
bx '
b0 &
x%
x$
x#
x"
0!
$end
#5
0%
0#
0"
1$
b1 &
0)
b0 '
b11 (
1!
#10
0!
#15
1"
0$
b10 &
0)
b1 '
b11 (
1!
#20
0!
#25
1#
0"
b11 &
0)
b10 '
b11 (
1!
#30
0!
#35
1%
0#
b0 &
1)
b11 '
b11 (
1!
#40
0!
#45
0%
1$
b1 &
0)
b0 '
b11 (
1!
#50
0!
#55
1"
0$
b10 &
0)
b1 '
b11 (
1!
#60
0!
#65
1#
0"
b11 &
0)
b10 '
b11 (
1!
#70
0!
#75
1%
0#
b0 &
1)
b11 '
b11 (
1!
#80
0!
#85
0%
1$
b1 &
0)
b0 '
b11 (
1!
#90
0!
#95
1"
0$
b10 &
0)
b1 '
b11 (
1!
#100
0!
#105
1#
0"
b11 &
0)
b10 '
b11 (
1!
#110
0!
#115
1%
0#
b0 &
1)
b11 '
b11 (
1!
#120
0!
#125
0%
1$
b1 &
0)
b0 '
b11 (
1!
#130
0!
#135
1"
0$
b10 &
0)
b1 '
b11 (
1!
#140
0!
#145
1#
0"
b11 &
0)
b10 '
b11 (
1!
#150
0!
#155
1%
0#
b0 &
1)
b11 '
b11 (
1!
#160
0!
#165
0%
1$
b1 &
0)
b0 '
b11 (
1!
#170
0!
#175
1"
0$
b10 &
0)
b1 '
b11 (
1!
#180
0!
#185
1#
0"
b11 &
0)
b10 '
b11 (
1!
#190
0!
#195
1%
0#
b0 &
1)
b11 '
b11 (
1!
