cpu15/reg_dc.v
module reg_dc(CLK_DC, N_REG_IN, 
              REG0, REG1, REG2, REG3, REG4, REG5, REG6, REG7, 
              N_REG_OUT, REG_OUT);
              
    input           CLK_DC;
    input   [2:0]   N_REG_IN;
    input   [15:0]  REG0, REG1, REG2, REG3, REG4, REG5, REG6, REG7;
    output  [2:0]   N_REG_OUT;
    output  [15:0]  REG_OUT;

    reg     [2:0]   N_REG_OUT;
    reg     [15:0]  REG_OUT;

    function [15:0] reg_out;
        input   [2:0]   n_reg_in;
        input   [15:0]  reg0, reg1, reg2, reg3, reg4, reg5, reg6, reg7;

        case (n_reg_in)
            3'b000: reg_out = reg0;
            3'b001: reg_out = reg1;
            3'b010: reg_out = reg2;
            3'b011: reg_out = reg3;
            3'b100: reg_out = reg4;
            3'b101: reg_out = reg5;
            3'b110: reg_out = reg6;
            3'b111: reg_out = reg7;
            default: reg_out = 16'bxxxx;  // 不定値
        endcase
    endfunction

    always @ (posedge CLK_DC) begin
        N_REG_OUT <= N_REG_IN;
        REG_OUT <= reg_out(N_REG_IN, REG0, REG1, REG2, REG3, REG4, REG5, REG6, REG7);
    end

endmodule

cpu15/test_reg_dc.v
module REG_DC_TEST();
    reg             clk_dc;
    reg     [2:0]   n_reg_in;
    reg     [15:0]  reg0, reg1, reg2, reg3, reg4, reg5, reg6, reg7;
    wire    [2:0]   n_reg_out;
    wire    [15:0]  reg_out;

    reg_dc reg_dc_inst(
        .CLK_DC(clk_dc), 
        .N_REG_IN(n_reg_in), 
        .REG0(reg0),
        .REG1(reg1),
        .REG2(reg2),
        .REG3(reg3),
        .REG4(reg4),
        .REG5(reg5),
        .REG6(reg6),
        .REG7(reg7),
        .N_REG_OUT(n_reg_out), 
        .REG_OUT(reg_out)
    );

    initial begin
        $dumpfile("test_reg_dc.vcd");
        $dumpvars(0, reg_dc_inst);
        $monitor("%t: n_reg_in=%b => n_reg_out=%b, reg_out=%h", $time, n_reg_in, n_reg_out, reg_out);
    end    

    // テスト信号の発生
    initial begin
        clk_dc <= 1'b0;
        reg0 <= 16'h6535;
        reg1 <= 16'h7628;
        reg2 <= 16'h7e6e;
        reg3 <= 16'habcd;
        reg4 <= 16'h64a6;
        reg5 <= 16'h0000;
        reg6 <= 16'h34b1;
        reg7 <= 16'h808d;
    end

    always #5 begin
        clk_dc <= !clk_dc;
    end

    initial begin
      #10
        n_reg_in <= 3'b000;
      #10
        n_reg_in <= 3'b001;
      #10
        n_reg_in <= 3'b010;
      #10
        n_reg_in <= 3'b011;
      #10
        n_reg_in <= 3'b100;
      #10
        n_reg_in <= 3'b101;
      #10
        n_reg_in <= 3'b110;
      #10
        n_reg_in <= 3'b111;
      #10
      $finish;
    end

endmodule

cpu15/test_reg_dc.vcd
$date
	Sat Sep  5 17:38:03 2020
$end
$version
	Icarus Verilog
$end
$timescale
	1s
$end
$scope module REG_DC_TEST $end
$scope module reg_dc_inst $end
$var wire 1 ! CLK_DC $end
$var wire 3 " N_REG_IN [2:0] $end
$var wire 16 # REG0 [15:0] $end
$var wire 16 $ REG1 [15:0] $end
$var wire 16 % REG2 [15:0] $end
$var wire 16 & REG3 [15:0] $end
$var wire 16 ' REG4 [15:0] $end
$var wire 16 ( REG5 [15:0] $end
$var wire 16 ) REG6 [15:0] $end
$var wire 16 * REG7 [15:0] $end
$var reg 3 + N_REG_OUT [2:0] $end
$var reg 16 , REG_OUT [15:0] $end
$scope function reg_out $end
$var reg 3 - n_reg_in [2:0] $end
$var reg 16 . reg0 [15:0] $end
$var reg 16 / reg1 [15:0] $end
$var reg 16 0 reg2 [15:0] $end
$var reg 16 1 reg3 [15:0] $end
$var reg 16 2 reg4 [15:0] $end
$var reg 16 3 reg5 [15:0] $end
$var reg 16 4 reg6 [15:0] $end
$var reg 16 5 reg7 [15:0] $end
$var reg 16 6 reg_out [15:0] $end
$upscope $end
$upscope $end
$upscope $end
$enddefinitions $end
#0
$dumpvars
bx 6
bx 5
bx 4
bx 3
bx 2
bx 1
bx 0
bx /
bx .
bx -
bx ,
bx +
b1000000010001101 *
b11010010110001 )
b0 (
b110010010100110 '
b1010101111001101 &
b111111001101110 %
b111011000101000 $
b110010100110101 #
bx "
0!
$end
#5
b110010100110101 .
b111011000101000 /
b111111001101110 0
b1010101111001101 1
b110010010100110 2
b0 3
b11010010110001 4
b1000000010001101 5
1!
#10
0!
b0 "
#15
b110010100110101 ,
b0 +
b110010100110101 6
b0 -
1!
#20
0!
b1 "
#25
b111011000101000 ,
b1 +
b111011000101000 6
b1 -
1!
#30
0!
b10 "
#35
b111111001101110 ,
b10 +
b111111001101110 6
b10 -
1!
#40
0!
b11 "
#45
b1010101111001101 ,
b11 +
b1010101111001101 6
b11 -
1!
#50
0!
b100 "
#55
b110010010100110 ,
b100 +
b110010010100110 6
b100 -
1!
#60
0!
b101 "
#65
b0 ,
b101 +
b0 6
b101 -
1!
#70
0!
b110 "
#75
b11010010110001 ,
b110 +
b11010010110001 6
b110 -
1!
#80
0!
b111 "
#85
b1000000010001101 ,
b111 +
b1000000010001101 6
b111 -
1!
