cpu15/decode.v
module decode(CLK_DC, PROM_OUT, OP_CODE, OP_DATA);
    input           CLK_DC;
    input   [14:0]  PROM_OUT;
    output  [3:0]   OP_CODE;
    output  [7:0]   OP_DATA;
    reg     [3:0]   OP_CODE;
    reg     [7:0]   OP_DATA;

    always @ (posedge CLK_DC) begin
        OP_CODE <= PROM_OUT[14:11];
        OP_DATA <= PROM_OUT[7:0];
    end

endmodule

cpu15/test_decode.v
module DECODE_TEST();
    reg             clk_dc;
    reg     [14:0]  prom_out;
    wire    [3:0]   op_code;
    wire    [7:0]   op_data;

    decode decode_inst(
        .CLK_DC(clk_dc),
        .PROM_OUT(prom_out),
        .OP_CODE(op_code),
        .OP_DATA(op_data)
    );

    initial begin
        $dumpfile("test_decode.vcd");
        $dumpvars(0, decode_inst);
        $monitor("%t: prom_out=%h => op_code=%h, op_data=%h", $time, prom_out, op_code, op_data);
    end    

    // テスト信号の発生
    initial begin
        clk_dc <= 1'b0;
    end

    always #5 begin
        clk_dc <= !clk_dc;
    end

    initial begin
      #10
        prom_out <= 15'b100100000000000;  // -- ldh Reg0, 0
      #10
        prom_out <= 15'b100000000000000;  // -- ldl Reg0, 0
      #10
        prom_out <= 15'b100100100000000;  // -- ldh Reg1, 0
      #10
        prom_out <= 15'b100000100000000;  // -- ldl Reg1, 1
      #10
        prom_out <= 15'b100101000000000;  // -- ldh Reg2, 0
      #10
        prom_out <= 15'b100001000000000;  // -- ldl Reg2, 0
      #10
        prom_out <= 15'b100101100000000;  // -- ldh Reg3, 0
      #10
        prom_out <= 15'b100001100000000;  // -- ldl Reg3, 10
      #10
        prom_out <= 15'b000101000100000;  // -- add Reg2, Reg1
      #10
        prom_out <= 15'b000100001000000;  // -- add Reg0, Reg2
      #10
        prom_out <= 15'b111000001000000;  // -- st Reg0, 64(0x
      #10
        prom_out <= 15'b101001001100000;  // -- cmp Reg2, R
      #10
        prom_out <= 15'b101100000001110;  // -- je 14(0x0e)
      #10
        prom_out <= 15'b110000000001000;  // -- jmp
      #10
        prom_out <= 15'b111100000000000;  // -- hlt
      #10
        prom_out <= 15'b100100000000000;  // -- nop
      #10
      $finish;
    end

endmodule

cpu15/test_decode.vcd
$date
	Sat Sep  5 16:35:08 2020
$end
$version
	Icarus Verilog
$end
$timescale
	1s
$end
$scope module DECODE_TEST $end
$scope module decode_inst $end
$var wire 1 ! CLK_DC $end
$var wire 15 " PROM_OUT [14:0] $end
$var reg 4 # OP_CODE [3:0] $end
$var reg 8 $ OP_DATA [7:0] $end
$upscope $end
$upscope $end
$enddefinitions $end
#0
$dumpvars
bx $
bx #
bx "
0!
$end
#5
1!
#10
0!
b100100000000000 "
#15
b0 $
b1001 #
1!
#20
0!
b100000000000000 "
#25
b1000 #
1!
#30
0!
b100100100000000 "
#35
b1001 #
1!
#40
0!
b100000100000000 "
#45
b1000 #
1!
#50
0!
b100101000000000 "
#55
b1001 #
1!
#60
0!
b100001000000000 "
#65
b1000 #
1!
#70
0!
b100101100000000 "
#75
b1001 #
1!
#80
0!
b100001100000000 "
#85
b1000 #
1!
#90
0!
b101000100000 "
#95
b100000 $
b1 #
1!
#100
0!
b100001000000 "
#105
b1000000 $
1!
#110
0!
b111000001000000 "
#115
b1110 #
1!
#120
0!
b101001001100000 "
#125
b1100000 $
b1010 #
1!
#130
0!
b101100000001110 "
#135
b1110 $
b1011 #
1!
#140
0!
b110000000001000 "
#145
b1000 $
b1100 #
1!
#150
0!
b111100000000000 "
#155
b0 $
b1111 #
1!
#160
0!
b100100000000000 "
#165
b1001 #
1!
