cpu15/fetch.v
module fetch(CLK_FT, P_COUNT, PROM_OUT);
    input           CLK_FT;
    input   [7:0]   P_COUNT;
    output  [14:0]  PROM_OUT;
    reg     [14:0]  PROM_OUT;
    // reg     [14:0]  memory[15:0];

    function [14:0] rom;
        input [7:0] addr;
        begin
            case (addr)
                8'h00: rom = 15'b100100000000000;  // -- ldh Reg0, 0
                8'h01: rom = 15'b100000000000000;  // -- ldl Reg0, 0
                8'h02: rom = 15'b100100100000000;  // -- ldh Reg1, 0
                8'h03: rom = 15'b100000100000000;  // -- ldl Reg1, 1
                8'h04: rom = 15'b100101000000000;  // -- ldh Reg2, 0
                8'h05: rom = 15'b100001000000000;  // -- ldl Reg2, 0
                8'h06: rom = 15'b100101100000000;  // -- ldh Reg3, 0
                8'h07: rom = 15'b100001100000000;  // -- ldl Reg3, 10
                8'h08: rom = 15'b000101000100000;  // -- add Reg2, Reg1
                8'h09: rom = 15'b000100001000000;  // -- add Reg0, Reg2
                8'h10: rom = 15'b111000001000000;  // -- st Reg0, 64(0x40)
                8'h11: rom = 15'b101001001100000;  // -- cmp Reg2, Reg3
                8'h12: rom = 15'b101100000001110;  // -- je 14(0x0e)
                8'h13: rom = 15'b110000000001000;  // -- jmp 8(0x08)
                8'h14: rom = 15'b111100000000000;  // -- hlt
                8'h15: rom = 15'b100100000000000;  // -- nop
            endcase

            // assign memory[0]  = 15'b100100000000000;  // -- ldh Reg0, 0
            // assign memory[1]  = 15'b100000000000000;  // -- ldl Reg0, 0
            // assign memory[2]  = 15'b100100100000000;  // -- ldh Reg1, 0
            // assign memory[3]  = 15'b100000100000000;  // -- ldl Reg1, 1
            // assign memory[4]  = 15'b100101000000000;  // -- ldh Reg2, 0
            // assign memory[5]  = 15'b100001000000000;  // -- ldl Reg2, 0
            // assign memory[6]  = 15'b100101100000000;  // -- ldh Reg3, 0
            // assign memory[7]  = 15'b100001100000000;  // -- ldl Reg3, 10
            // assign memory[8]  = 15'b000101000100000;  // -- add Reg2, Reg1
            // assign memory[9]  = 15'b000100001000000;  // -- add Reg0, Reg2
            // assign memory[10] = 15'b111000001000000;  // -- st Reg0, 64(0x40)
            // assign memory[11] = 15'b101001001100000;  // -- cmp Reg2, Reg3
            // assign memory[12] = 15'b101100000001110;  // -- je 14(0x0e)
            // assign memory[13] = 15'b110000000001000;  // -- jmp 8(0x08)
            // assign memory[14] = 15'b111100000000000;  // -- hlt
            // assign memory[15] = 15'b100100000000000;  // -- nop

            // always @ (posedge CLK_FT) begin
            //     PROM_OUT <= memory[P_COUNT[3:0]];
            // end
        end
    endfunction

    always @ (posedge CLK_FT) begin
        PROM_OUT <= rom(P_COUNT);
    end

endmodule

cpu15/test_fetch.v
// `define HCYCL 10
// `timescale 1ns / 1ps

module FETCH_TEST();
    // parameter STEP = 10; // 10ナノ秒：100MHz
    // parameter TICKS = 19;

    reg             clk_ft;
    reg     [7:0]   p_count;
    wire    [14:0]  prom_out;

    fetch fetch_inst(
        .CLK_FT(clk_ft),
        .P_COUNT(p_count), 
        .PROM_OUT(prom_out)
    );

    initial begin
        $dumpfile("test_fetch.vcd");
        $dumpvars(0, fetch_inst);
        $monitor("%t: p_count=%h, prom_out=%b", $time, p_count, prom_out);
    end

    // initial begin
    //     clk_ft = 0;
    //     forever #`HCYCL clk_ft = !clk_ft;
    // end

    // initial begin
    //     repeat (TICKS) @(posedge clk_ft);
    //     $finish;
    // end

    // テスト信号の発生
    initial begin
        clk_ft <= 1'b0;
    //   #200
    //     $finish;
    end

    always #5 begin
        clk_ft <= !clk_ft;
    end

    // initial begin
    //     p_count <= 8'h00;
    // end

    // always @(posedge clk_ft) begin
    //     p_count <= 8'b01;
    // end

    initial begin
      #10
        p_count <= 8'h00;
      #10
        p_count <= 8'h01;
      #10
        p_count <= 8'h02;
      #10
        p_count <= 8'h03;
      #10
        p_count <= 8'h04;
      #10
        p_count <= 8'h05;
      #10
        p_count <= 8'h06;
      #10
        p_count <= 8'h07;
      #10
        p_count <= 8'h08;
      $finish;
    end

endmodule

cpu15/test_fetch.vcd
$date
	Sat Sep  5 12:11:47 2020
$end
$version
	Icarus Verilog
$end
$timescale
	1s
$end
$scope module FETCH_TEST $end
$scope module fetch_inst $end
$var wire 1 ! CLK_FT $end
$var wire 8 " P_COUNT [7:0] $end
$var reg 15 # PROM_OUT [14:0] $end
$scope function rom $end
$var reg 8 $ addr [7:0] $end
$var reg 15 % rom [14:0] $end
$upscope $end
$upscope $end
$upscope $end
$enddefinitions $end
#0
$dumpvars
bx %
bx $
bx #
bx "
0!
$end
#5
1!
#10
0!
b0 "
#15
b100100000000000 #
b100100000000000 %
b0 $
1!
#20
0!
b1 "
#25
b100000000000000 #
b100000000000000 %
b1 $
1!
#30
0!
b10 "
#35
b100100100000000 #
b100100100000000 %
b10 $
1!
#40
0!
b11 "
#45
b100000100000000 #
b100000100000000 %
b11 $
1!
#50
0!
b100 "
#55
b100101000000000 #
b100101000000000 %
b100 $
1!
#60
0!
b101 "
#65
b100001000000000 #
b100001000000000 %
b101 $
1!
#70
0!
b110 "
#75
b100101100000000 #
b100101100000000 %
b110 $
1!
#80
0!
b111 "
#85
b100001100000000 #
b100001100000000 %
b111 $
1!
#90
0!
b1000 "
