cpu15/reg_wb.v
module reg_wb(CLK_WB,
              RESET_N,
              N_REG,
              REG_IN,
              REG_WEN,
              REG_0,
              REG_1,
              REG_2,
              REG_3,
              REG_4,
              REG_5,
              REG_6,
              REG_7);
    input           CLK_WB;
    input           RESET_N;
    input   [2:0]   N_REG;
    input   [15:0]  REG_IN;
    input           REG_WEN;
    output  [15:0]  REG_0, REG_1, REG_2, REG_3, REG_4, REG_5, REG_6, REG_7;

    reg     [15:0]  REG_0, REG_1, REG_2, REG_3, REG_4, REG_5, REG_6, REG_7;

    always @ (posedge CLK_WB) begin
        if (RESET_N == 1'b0) begin
            REG_0 <= 16'h0000;
            REG_1 <= 16'h0000;
            REG_2 <= 16'h0000;
            REG_3 <= 16'h0000;
            REG_4 <= 16'h0000;
            REG_5 <= 16'h0000;
            REG_6 <= 16'h0000;
            REG_7 <= 16'h0000;
        end
        else if (REG_WEN == 1'b1) begin
            case (N_REG)
                3'b000: REG_0 <= REG_IN;
                3'b001: REG_1 <= REG_IN;
                3'b010: REG_2 <= REG_IN;
                3'b011: REG_3 <= REG_IN;
                3'b100: REG_4 <= REG_IN;
                3'b101: REG_5 <= REG_IN;
                3'b110: REG_6 <= REG_IN;
                3'b111: REG_7 <= REG_IN;
            endcase
        end
    end

endmodule

cpu15/test_reg_wb.v
module REG_WB_TEST();
    reg             clk_wb;
    reg             reset_n;
    reg     [2:0]   n_reg;
    reg     [15:0]  reg_in;
    reg             reg_wen;
    wire    [15:0]  reg_0;
    wire    [15:0]  reg_1;
    wire    [15:0]  reg_2;
    wire    [15:0]  reg_3;
    wire    [15:0]  reg_4;
    wire    [15:0]  reg_5;
    wire    [15:0]  reg_6;
    wire    [15:0]  reg_7;

    reg_wb reg_wb_inst(
        .CLK_WB(clk_wb),
        .RESET_N(reset_n),
        .N_REG(n_reg),
        .REG_IN(reg_in),
        .REG_WEN(reg_wen),
        .REG_0(reg_0),
        .REG_1(reg_1),
        .REG_2(reg_2),
        .REG_3(reg_3),
        .REG_4(reg_4),
        .REG_5(reg_5),
        .REG_6(reg_6),
        .REG_7(reg_7)
    );

    initial begin
        $dumpfile("test_reg_wb.vcd");
        $dumpvars(0, reg_wb_inst);
        $monitor("%t: reset_n=%b, n_reg=%b, reg_in=%h, reg_wen=%b => reg_0=%h, reg_1=%h, reg_2=%h, reg_3=%h, reg_4=%h, reg_5=%h, reg_6=%h, reg_7=%h", $time, reset_n, n_reg, reg_in, reg_wen, reg_0, reg_1, reg_2, reg_3, reg_4, reg_5, reg_6, reg_7);
    end

    // テスト信号の発生
    initial begin
        clk_wb <= 1'b0;
        // reset_n <= 1'b0;
        // reg_wen <= 1'b0;
        // reg_0 <= 16'h6535;
        // reg_1 <= 16'h7628;
        // reg_2 <= 16'h7e6e;
        // reg_3 <= 16'habcd;
        // reg_4 <= 16'h64a6;
        // reg_5 <= 16'h0000;
        // reg_6 <= 16'h34b1;
        // reg_7 <= 16'h808d;
    end

    always #5 begin
        clk_wb <= !clk_wb;
    end

    initial begin
      #10
        reset_n <= 1'b1;
        n_reg <= 3'b000;
        reg_in <= 16'hbeaf;
        reg_wen <= 1'b0;
      #10
        n_reg <= 3'b001;
        reg_in <= 16'hbeaf;
        reg_wen <= 1'b1;
      #10
        n_reg <= 3'b010;
        reg_in <= 16'hbeaf;
        reg_wen <= 1'b0;
      #10
        n_reg <= 3'b011;
        reg_in <= 16'hbeaf;
        reg_wen <= 1'b1;
      #10
        reset_n <= 1'b0;
      #10
        n_reg <= 3'b100;
        reg_in <= 16'hbeaf;
        reg_wen <= 1'b0;
      #10
        n_reg <= 3'b101;
        reg_in <= 16'hbeaf;
        reg_wen <= 1'b1;
      #10
        reset_n <= 1'b1;
        n_reg <= 3'b110;
        reg_in <= 16'hbeaf;
        reg_wen <= 1'b0;
      #10
        n_reg <= 3'b111;
        reg_in <= 16'hbeaf;
        reg_wen <= 1'b1;
      #10
      $finish;
    end

endmodule

cpu15/test_reg_wb.vcd
$date
	Sat Sep 19 16:51:10 2020
$end
$version
	Icarus Verilog
$end
$timescale
	1s
$end
$scope module REG_WB_TEST $end
$scope module reg_wb_inst $end
$var wire 1 ! CLK_WB $end
$var wire 3 " N_REG [2:0] $end
$var wire 16 # REG_IN [15:0] $end
$var wire 1 $ REG_WEN $end
$var wire 1 % RESET_N $end
$var reg 16 & REG_0 [15:0] $end
$var reg 16 ' REG_1 [15:0] $end
$var reg 16 ( REG_2 [15:0] $end
$var reg 16 ) REG_3 [15:0] $end
$var reg 16 * REG_4 [15:0] $end
$var reg 16 + REG_5 [15:0] $end
$var reg 16 , REG_6 [15:0] $end
$var reg 16 - REG_7 [15:0] $end
$upscope $end
$upscope $end
$enddefinitions $end
#0
$dumpvars
bx -
bx ,
bx +
bx *
bx )
bx (
bx '
bx &
x%
x$
bx #
bx "
0!
$end
#5
1!
#10
0!
0$
b1011111010101111 #
b0 "
1%
#15
1!
#20
0!
1$
b1 "
#25
b1011111010101111 '
1!
#30
0!
0$
b10 "
#35
1!
#40
0!
1$
b11 "
#45
b1011111010101111 )
1!
#50
0!
0%
#55
b0 -
b0 ,
b0 +
b0 *
b0 )
b0 (
b0 '
b0 &
1!
#60
0!
0$
b100 "
#65
1!
#70
0!
1$
b101 "
#75
1!
#80
0!
0$
b110 "
1%
#85
1!
#90
0!
1$
b111 "
#95
b1011111010101111 -
1!
